amocrm/__init__.py
amocrm/v2/__init__.py
amocrm/v2/account.py
amocrm/v2/cli.py
amocrm/v2/exceptions.py
amocrm/v2/fields.py
amocrm/v2/filters.py
amocrm/v2/interaction.py
amocrm/v2/links.py
amocrm/v2/manager.py
amocrm/v2/model.py
amocrm/v2/register.py
amocrm/v2/tokens.py
amocrm/v2/entity/__init__.py
amocrm/v2/entity/call.py
amocrm/v2/entity/company.py
amocrm/v2/entity/contact.py
amocrm/v2/entity/custom_field.py
amocrm/v2/entity/customer.py
amocrm/v2/entity/events.py
amocrm/v2/entity/lead.py
amocrm/v2/entity/list.py
amocrm/v2/entity/note.py
amocrm/v2/entity/pipeline.py
amocrm/v2/entity/tag.py
amocrm/v2/entity/task.py
amocrm/v2/entity/user.py
amocrm_api-2.6.1.dist-info/LICENSE.txt
amocrm_api-2.6.1.dist-info/METADATA
amocrm_api-2.6.1.dist-info/WHEEL
amocrm_api-2.6.1.dist-info/entry_points.txt
amocrm_api-2.6.1.dist-info/top_level.txt
amocrm_api-2.6.1.dist-info/RECORD
