Metadata-Version: 2.1
Name: amocrm_api
Version: 2.6.1
Summary: Python API for Amocrm
Home-page: https://github.com/Krukov/amocrm_api
Download-URL: https://github.com/Krukov/amocrm_api/tarball/2.6.1
Author: Dmitry Kryukov
Author-email: glebov.ru@gmail.com
License: MIT license
Classifier: Development Status :: 4 - Beta
Classifier: Intended Audience :: Developers
Classifier: License :: OSI Approved :: MIT License
Classifier: Programming Language :: Python
Classifier: Programming Language :: Python :: 3
Classifier: Programming Language :: Python :: 3.6
Classifier: Programming Language :: Python :: 3.7
Classifier: Programming Language :: Python :: 3.8
Classifier: Programming Language :: Python :: 3.9
Classifier: Programming Language :: Python :: 3.10
Classifier: Topic :: Software Development :: Libraries :: Python Modules
Requires-Python: >=3.6
Provides-Extra: cli
License-File: LICENSE.txt
